windnd/__init__.py
windnd/windnd.py
windnd-1.0.6.dist-info/COPYING.txt
windnd-1.0.6.dist-info/METADATA
windnd-1.0.6.dist-info/WHEEL
windnd-1.0.6.dist-info/top_level.txt
windnd-1.0.6.dist-info/zip-safe
windnd-1.0.6.dist-info/RECORD
