Metadata-Version: 2.1
Name: windnd
Version: 1.0.6
Summary: windows drag icon & drop load.
Home-page: https://pypi.org/project/windnd/
Author: vilame
Author-email: opaquism@hotmail.com
License: MIT
Keywords: windnd
Platform: UNKNOWN
Classifier: License :: OSI Approved :: MIT License
Classifier: Programming Language :: Python
Classifier: Intended Audience :: Developers
